Metadata-Version: 2.1
Name: DirTreeGenerator
Version: 1.1
Summary: This Module can generate tree of files in directory.
Home-page: UNKNOWN
Author-email: max.taran.210@mail.ru
License: UNKNOWN
Platform: UNKNOWN
